TextTron/TextTron.py
TextTron/__init__.py
TextTron-0.45.dist-info/LICENSE
TextTron-0.45.dist-info/METADATA
TextTron-0.45.dist-info/WHEEL
TextTron-0.45.dist-info/top_level.txt
TextTron-0.45.dist-info/RECORD
