Metadata-Version: 2.1
Name: TextTron
Version: 0.45
Summary: TextTron is a simple light-weight image processing based text detector in document images.
Home-page: https://github.com/AyanGadpal/TextTron-Lightweight-text-detector
Author: Ayan Gadpal
Author-email: ayangadpal2@gmail.com
License: MIT
Keywords: Text Detection,lightweight Text Detection,Document Text Detector
Platform: UNKNOWN
Requires: opencv_python
Requires: numpy
